subprocess_multitee.py
subprocess_multitee-0.2.1.dist-info/METADATA
subprocess_multitee-0.2.1.dist-info/WHEEL
subprocess_multitee-0.2.1.dist-info/licenses/LICENSE
subprocess_multitee-0.2.1.dist-info/RECORD
