Metadata-Version: 2.4
Name: subprocess-multitee
Version: 0.2.1
Summary: A small `tee` function for splitting stdout/stderr in subprocess, and a `subprocess.Popen` convenience wrapper
Project-URL: Homepage, https://github.com/JasonGross/subprocess-multitee
Project-URL: Bug Tracker, https://github.com/JasonGross/subprocess-multitee/issues
Author-email: Jason Gross <jgross@mit.edu>
License-File: LICENSE
Requires-Python: >=3.6
